{
  "manifestVersion": 1,
  "id": "vsts-tools-build-extensions",
  "name": "VSTS-Tools Build Extensions",
  "version": "1.0.0",
  "publisher": "moonspace-labs-llc",
  "targets": [
    {
      "id": "Microsoft.VisualStudio.Services"
    }
  ],
  "description": "Various build tasks to help extend diagnostics, retention setting, etc.",
  "categories": [
    "Build and release"
  ],
  "tags": [
    "diagnostics",
    "list files",
    "list folders"
  ],
  "screenshots": [
    {
      "path": "screenshots/extensions.png"
    }
  ],
  "content": {
    "details": {
      "path": "overview.md"
    }
  },
  "icons": {
    "default": "extension-icon.png"
  },
  "files": [
    {
      "path": "VSTSToolsListFiles"
    },
    {
      "path": "VSTSToolsListVariables"
    }
  ],
  "scopes": [
    "vso.build_execute"
  ],
  "contributions": [
    {
      "id": "vsts-ListFiles",
      "type": "ms.vss-distributed-task.task",
      "targets": [
        "ms.vss-distributed-task.tasks"
      ],
      "properties": {
        "name": "VSTSToolsListFiles"
      }
    },
    {
      "id": "vsts-ListVariables",
      "type": "ms.vss-distributed-task.task",
      "targets": [
        "ms.vss-distributed-task.tasks"
      ],
      "properties": {
        "name": "VSTSToolsListVariables"
      }
    }
  ],
  "links": {
    "home": {
      "uri": "https://blog.devmatter.com"
    },
    "getstarted": {
      "uri": "http://blog.devmatter.com/vsts-tools-now-on-github/"
    },
    "repository": {
      "uri": "https://github.com/jbramwell/VSTS-Tools"
    },
    "support": {
      "uri": "https://github.com/jbramwell/VSTS-Tools/issues"
    },
    "issues": {
      "uri": "https://github.com/jbramwell/VSTS-Tools/issues"
    }
  },
  "branding": {
    "color": "#1EA5CE",
    "theme": "dark"
  }
}